local_coze/__init__.py
local_coze/cli/__init__.py
local_coze/cli/chat.py
local_coze/cli/cli.py
local_coze/cli/constants.py
local_coze/cli/db.py
local_coze/cli/embedding.py
local_coze/cli/image.py
local_coze/cli/knowledge.py
local_coze/cli/search.py
local_coze/cli/utils.py
local_coze/cli/video.py
local_coze/cli/video_edit.py
local_coze/cli/voice.py
local_coze/core/__init__.py
local_coze/core/client.py
local_coze/core/config.py
local_coze/core/exceptions.py
local_coze/database/__init__.py
local_coze/database/client.py
local_coze/database/migration.py
local_coze/embedding/__init__.py
local_coze/embedding/client.py
local_coze/embedding/models.py
local_coze/image/__init__.py
local_coze/image/client.py
local_coze/image/models.py
local_coze/knowledge/__init__.py
local_coze/knowledge/client.py
local_coze/knowledge/models.py
local_coze/llm/__init__.py
local_coze/llm/client.py
local_coze/llm/models.py
local_coze/memory/__init__.py
local_coze/memory/client.py
local_coze/s3/__init__.py
local_coze/s3/client.py
local_coze/s3/models.py
local_coze/search/__init__.py
local_coze/search/client.py
local_coze/search/models.py
local_coze/video/__init__.py
local_coze/video/client.py
local_coze/video/models.py
local_coze/video_edit/__init__.py
local_coze/video_edit/examples.py
local_coze/video_edit/frame_extractor.py
local_coze/video_edit/models.py
local_coze/video_edit/video_edit.py
local_coze/voice/__init__.py
local_coze/voice/asr.py
local_coze/voice/models.py
local_coze/voice/tts.py
local_coze-0.1.0.dist-info/METADATA
local_coze-0.1.0.dist-info/WHEEL
local_coze-0.1.0.dist-info/entry_points.txt
local_coze-0.1.0.dist-info/licenses/LICENSE
local_coze-0.1.0.dist-info/RECORD
