Metadata-Version: 2.4
Name: local-coze
Version: 0.1.0
Summary: Local Coze SDK - 优雅的多功能 AI SDK，支持图片生成、视频生成、语音合成、语音识别、大语言模型、联网搜索和文本/多模态 Embedding。包含命令行工具 local-coze，支持 Context 上下文追踪
License: MIT
License-File: LICENSE
Keywords: coze,coze-coding,integration,ai,sdk,image-generation,video-generation,text-to-speech,speech-recognition,llm,search,embedding,vector-embedding,semantic-search,rag,doubao,seedream
Author: Coze Coding Integration Team
Author-email: support@coze.com
Maintainer: Coze Coding Integration Team
Maintainer-email: support@coze.com
Requires-Python: >=3.11
Classifier: Development Status :: 4 - Beta
Classifier: Intended Audience :: Developers
Classifier: License :: OSI Approved :: MIT License
Classifier: Operating System :: OS Independent
Classifier: Programming Language :: Python :: 3
Classifier: Programming Language :: Python :: 3.11
Classifier: Programming Language :: Python :: 3.12
Classifier: Programming Language :: Python :: 3.13
Classifier: Programming Language :: Python :: 3.14
Classifier: Topic :: Multimedia :: Graphics
Classifier: Topic :: Multimedia :: Sound/Audio
Classifier: Topic :: Multimedia :: Video
Classifier: Topic :: Scientific/Engineering :: Artificial Intelligence
Classifier: Topic :: Software Development :: Libraries :: Python Modules
Requires-Dist: alembic (>=1.13.0)
Requires-Dist: boto3 (>=1.26.0)
Requires-Dist: click (>=8.0.0)
Requires-Dist: coze-coding-utils (>=0.1.0)
Requires-Dist: cozeloop (>=0.1.0)
Requires-Dist: langchain-core (>=0.1.0)
Requires-Dist: langchain-openai (>=0.1.0)
Requires-Dist: langgraph (>=0.2.0)
Requires-Dist: langgraph-checkpoint-postgres (>=3.0.0)
Requires-Dist: psycopg-pool (>=3.0.0)
Requires-Dist: psycopg[binary] (>=3.0.0)
Requires-Dist: pydantic (>=2.0.0)
Requires-Dist: requests (>=2.31.0)
Requires-Dist: rich (>=13.0.0)
Requires-Dist: sqlacodegen (>=3.0.0)
Requires-Dist: sqlalchemy (>=2.0.0)
Project-URL: Changelog, https://github.com/coze/local-coze/blob/main/CHANGELOG.md
Project-URL: Documentation, https://github.com/coze/local-coze#readme
Project-URL: Homepage, https://github.com/coze/local-coze
Project-URL: Issues, https://github.com/coze/local-coze/issues
Project-URL: Repository, https://github.com/coze/local-coze
